mycalc/calculator.py
sejin230411-1.0.1.dist-info/METADATA
sejin230411-1.0.1.dist-info/WHEEL
sejin230411-1.0.1.dist-info/top_level.txt
sejin230411-1.0.1.dist-info/RECORD
