Metadata-Version: 2.1
Name: sejin230411
Version: 1.0.1
Summary: nice calc
Home-page: http://github.com/chunsejin/abc
Download-URL: http://github.com/chunsejin/abc/egfc.zip
Author: sjchun
License: UNKNOWN
Platform: UNKNOWN
Classifier: Programming Language :: Python :: 3
